{"frames": {

"monkey0.png":
{
	"frame": {"x":0,"y":0,"w":317,"h":801},
	"rotated": false,
	"trimmed": false,
	"spriteSourceSize": {"x":0,"y":0,"w":317,"h":801},
	"sourceSize": {"w":317,"h":801}
},
"monkey1.png":
{
	"frame": {"x":317,"y":0,"w":317,"h":801},
	"rotated": false,
	"trimmed": false,
	"spriteSourceSize": {"x":0,"y":0,"w":317,"h":801},
	"sourceSize": {"w":317,"h":801}
},
"monkey2.png":
{
	"frame": {"x":634,"y":0,"w":317,"h":801},
	"rotated": false,
	"trimmed": false,
	"spriteSourceSize": {"x":0,"y":0,"w":317,"h":801},
	"sourceSize": {"w":317,"h":801}
},
"monkey3.png":
{
	"frame": {"x":951,"y":0,"w":317,"h":801},
	"rotated": false,
	"trimmed": false,
	"spriteSourceSize": {"x":0,"y":0,"w":317,"h":801},
	"sourceSize": {"w":317,"h":801}
},
"monkey4.png":
{
	"frame": {"x":1268,"y":0,"w":317,"h":801},
	"rotated": false,
	"trimmed": false,
	"spriteSourceSize": {"x":0,"y":0,"w":317,"h":801},
	"sourceSize": {"w":317,"h":801}
},
"monkey5.png":
{
	"frame": {"x":1585,"y":0,"w":317,"h":801},
	"rotated": false,
	"trimmed": false,
	"spriteSourceSize": {"x":0,"y":0,"w":317,"h":801},
	"sourceSize": {"w":317,"h":801}
},
"monkey6.png":
{
	"frame": {"x":1902,"y":0,"w":317,"h":801},
	"rotated": false,
	"trimmed": false,
	"spriteSourceSize": {"x":0,"y":0,"w":317,"h":801},
	"sourceSize": {"w":317,"h":801}
},
"monkey7.png":
{
	"frame": {"x":2219,"y":0,"w":317,"h":801},
	"rotated": false,
	"trimmed": false,
	"spriteSourceSize": {"x":0,"y":0,"w":317,"h":801},
	"sourceSize": {"w":317,"h":801}
},
"monkey8.png":
{
	"frame": {"x":2536,"y":0,"w":317,"h":801},
	"rotated": false,
	"trimmed": false,
	"spriteSourceSize": {"x":0,"y":0,"w":317,"h":801},
	"sourceSize": {"w":317,"h":801}
},
"monkey9.png":
{
	"frame": {"x":2853,"y":0,"w":317,"h":801},
	"rotated": false,
	"trimmed": false,
	"spriteSourceSize": {"x":0,"y":0,"w":317,"h":801},
	"sourceSize": {"w":317,"h":801}
},
"monkey10.png":
{
	"frame": {"x":3170,"y":0,"w":317,"h":801},
	"rotated": false,
	"trimmed": false,
	"spriteSourceSize": {"x":0,"y":0,"w":317,"h":801},
	"sourceSize": {"w":317,"h":801}
},
"monkey11.png":
{
	"frame": {"x":0,"y":801,"w":317,"h":801},
	"rotated": false,
	"trimmed": false,
	"spriteSourceSize": {"x":0,"y":0,"w":317,"h":801},
	"sourceSize": {"w":317,"h":801}
},
"monkey12.png":
{
	"frame": {"x":317,"y":801,"w":317,"h":801},
	"rotated": false,
	"trimmed": false,
	"spriteSourceSize": {"x":0,"y":0,"w":317,"h":801},
	"sourceSize": {"w":317,"h":801}
},
"monkey13.png":
{
	"frame": {"x":634,"y":801,"w":317,"h":801},
	"rotated": false,
	"trimmed": false,
	"spriteSourceSize": {"x":0,"y":0,"w":317,"h":801},
	"sourceSize": {"w":317,"h":801}
},
"monkey14.png":
{
	"frame": {"x":951,"y":801,"w":317,"h":801},
	"rotated": false,
	"trimmed": false,
	"spriteSourceSize": {"x":0,"y":0,"w":317,"h":801},
	"sourceSize": {"w":317,"h":801}
},
"monkey15.png":
{
	"frame": {"x":1268,"y":801,"w":317,"h":801},
	"rotated": false,
	"trimmed": false,
	"spriteSourceSize": {"x":0,"y":0,"w":317,"h":801},
	"sourceSize": {"w":317,"h":801}
},
"monkey16.png":
{
	"frame": {"x":1585,"y":801,"w":317,"h":801},
	"rotated": false,
	"trimmed": false,
	"spriteSourceSize": {"x":0,"y":0,"w":317,"h":801},
	"sourceSize": {"w":317,"h":801}
},
"monkey17.png":
{
	"frame": {"x":1902,"y":801,"w":317,"h":801},
	"rotated": false,
	"trimmed": false,
	"spriteSourceSize": {"x":0,"y":0,"w":317,"h":801},
	"sourceSize": {"w":317,"h":801}
},
"monkey18.png":
{
	"frame": {"x":2219,"y":801,"w":317,"h":801},
	"rotated": false,
	"trimmed": false,
	"spriteSourceSize": {"x":0,"y":0,"w":317,"h":801},
	"sourceSize": {"w":317,"h":801}
},
"monkey19.png":
{
	"frame": {"x":2536,"y":801,"w":317,"h":801},
	"rotated": false,
	"trimmed": false,
	"spriteSourceSize": {"x":0,"y":0,"w":317,"h":801},
	"sourceSize": {"w":317,"h":801}
},
"monkey20.png":
{
	"frame": {"x":2853,"y":801,"w":317,"h":801},
	"rotated": false,
	"trimmed": false,
	"spriteSourceSize": {"x":0,"y":0,"w":317,"h":801},
	"sourceSize": {"w":317,"h":801}
}},
"meta": {
	"app": "http://www.codeandweb.com/texturepacker",
	"version": "1.0",
	"image": "monkey.png",
	"format": "RGBA8888",
	"size": {"w":3487,"h":1602},
	"scale": "1",
	"smartupdate": "$TexturePacker:SmartUpdate:af3748696e3dc960dc56d0993e3691f6:d52e7164f5c86c572c86acf7445fbc77:f22ec43fa8bb0df0abc56a901a4cbbb5$"
}
}
